sbol2excel/__init__.py
sbol2excel/column_methods.py
sbol2excel/converter.py
sbol2excel/helper_functions.py
sbol2excel/ontology_methods.py
sbol2excel/sheet_methods.py
sbol2excel/temo.py
sbol2excel/temp.py
sbol2excel/tempCodeRunnerFile.py
sbol2excel/Ontology Sheets/ontologies_v000.xlsx
sbol2excel/Ontology Sheets/ontologies_v001.xlsx
sbol2excel/Output_Templates/Output_Template_v001.xlsx
sbol2excel-1.0.0a23.dist-info/METADATA
sbol2excel-1.0.0a23.dist-info/WHEEL
sbol2excel-1.0.0a23.dist-info/top_level.txt
sbol2excel-1.0.0a23.dist-info/RECORD
