Metadata-Version: 2.1
Name: sbol2excel
Version: 1.0.0a23
Summary: convert sbol resources into excel
Home-page: https://github.com/SynBioDex/SBOL-to-Excel
Maintainer: Julian Abam
Maintainer-email: abamaj@gmail.com
License: BSD 3-clause
Platform: UNKNOWN
Requires-Dist: requests-html (>=0.10.0)
Requires-Dist: pandas (>=1.4.2)
Requires-Dist: openpyxl (>=3.0.10)
Requires-Dist: rdflib (>=6.1.1)
Requires-Dist: validators (>=0.19.0)
